{
  "parent": "minecraft:recipes/root",
  "criteria": {
    "has_talisman_paper": {
      "conditions": {
        "items": [
          {
            "items": "ascension:talisman_paper"
          }
        ]
      },
      "trigger": "minecraft:inventory_changed"
    },
    "has_the_recipe": {
      "conditions": {
        "recipe": "ascension:shaped/ancestor_journal"
      },
      "trigger": "minecraft:recipe_unlocked"
    }
  },
  "requirements": [
    [
      "has_the_recipe",
      "has_talisman_paper"
    ]
  ],
  "rewards": {
    "recipes": [
      "ascension:shaped/ancestor_journal"
    ]
  }
}